earthdata_mcp_server/__init__.py
earthdata_mcp_server/__main__.py
earthdata_mcp_server/__version__.py
earthdata_mcp_server/server.py
earthdata_mcp_server/examples/README.md
earthdata_mcp_server/examples/__init__.py
earthdata_mcp_server/examples/workflow_example.py
earthdata_mcp_server/tests/README.md
earthdata_mcp_server/tests/__init__.py
earthdata_mcp_server/tests/test_cli_options.py
earthdata_mcp_server/tests/test_composition.py
earthdata_mcp_server-0.4.0.dist-info/METADATA
earthdata_mcp_server-0.4.0.dist-info/WHEEL
earthdata_mcp_server-0.4.0.dist-info/entry_points.txt
earthdata_mcp_server-0.4.0.dist-info/licenses/LICENSE
earthdata_mcp_server-0.4.0.dist-info/RECORD
