Metadata-Version: 2.4
Name: earthdata_mcp_server
Version: 0.4.0
Project-URL: Home, https://github.com/datalayer/earthdata-mcp-server
Author-email: Datalayer <info@datalayer.io>
License: BSD 3-Clause License
License-File: LICENSE
Keywords: Earthdata
Classifier: Intended Audience :: Developers
Classifier: Intended Audience :: System Administrators
Classifier: License :: OSI Approved :: BSD License
Classifier: Programming Language :: Python
Classifier: Programming Language :: Python :: 3
Requires-Python: >=3.10
Requires-Dist: earthaccess
Requires-Dist: jupyter-mcp-server<1,>=0.12.0
Requires-Dist: mcp[cli]>=1.2.1
Requires-Dist: rich
Provides-Extra: lint
Requires-Dist: mdformat-gfm>=0.3.5; extra == 'lint'
Requires-Dist: mdformat>0.7; extra == 'lint'
Requires-Dist: ruff; extra == 'lint'
Provides-Extra: test
Requires-Dist: ipykernel; extra == 'test'
Requires-Dist: jupyter-server<3,>=1.6; extra == 'test'
Requires-Dist: pytest>=7.0; extra == 'test'
Provides-Extra: typing
Requires-Dist: mypy>=0.990; extra == 'typing'
